{
  "locale": "tr",
  "keyValues": {
    "permissions.articles.create.name": "Parça oluşturma",
    "permissions.articles.create.description": "Parça oluşturma izni.",
    "permissions.articles.edit.name": "Parça düzenleme",
    "permissions.articles.edit.description": "Parça düzenleme izni.",
    "permissions.articles.delete.name": "Parça silme",
    "permissions.articles.delete.description": "Parça silme izni.",
    "permissions.articles.get.full.name": "Parçaları görüntüleme, tam model",
    "permissions.articles.get.full.description": "Tam model ile parça arama izni.",
    "permissions.articles.get.main.name": "Parçaları görüntüleme, minimum model",
    "permissions.articles.get.main.description": "Minimum model ile parça arama izni.",
    "permissions.article.sizes.create.name": "Parça ölçülerini ayarlama",
    "permissions.article.sizes.create.description": "Parça ölçülerini ayarlama izni.",
    "permissions.article.sizes.get.name": "Parça ölçülerini görüntüleme",
    "permissions.article.sizes.get.description": "Parça ölçülerini görüntüleme izni.",
    "permissions.article.sizes.update.name": "Parça ölçülerini güncelleme",
    "permissions.article.sizes.update.description": "Parça ölçülerini güncelleme izni.",
    "permissions.article.sizes.delete.name": "Parça ölçülerini silme",
    "permissions.article.sizes.delete.description": "Parça ölçülerini silme izni.",
    "permissions.article.weight.create.name": "Parça ağırlığını ayarlama",
    "permissions.article.weight.create.description": "Parça ağırlığını ayarlama izni.",
    "permissions.article.weight.get.name": "Parça ağırlığını görüntüleme",
    "permissions.article.weight.get.description": "Parça ağırlığını görüntüleme izni.",
    "permissions.article.weight.update.name": "Parça ağırlığını güncelleme",
    "permissions.article.weight.update.description": "Parça ağırlığını güncelleme izni.",
    "permissions.article.weight.delete.name": "Parça ağırlığını silme",
    "permissions.article.weight.delete.description": "Parça ağırlığını silme izni.",
    "permissions.producers.create.name": "Üretici oluşturma",
    "permissions.producers.create.description": "Üretici oluşturma izni.",
    "permissions.producers.edit.name": "Üretici düzenleme",
    "permissions.producers.edit.description": "Üretici düzenleme izni.",
    "permissions.producers.delete.name": "Üretici silme",
    "permissions.producers.delete.description": "Üretici silme izni.",
    "permissions.article.characteristics.create.name": "Parça özelliği oluşturma",
    "permissions.article.characteristics.create.description": "Parça özellikleri oluşturma izni.",
    "permissions.article.characteristics.update.name": "Parça özelliği güncelleme",
    "permissions.article.characteristics.update.description": "Parça özellikleri güncelleme izni.",
    "permissions.article.characteristics.delete.name": "Parça özelliği silme",
    "permissions.article.characteristics.delete.description": "Parça özellikleri silme izni.",
    "permissions.article.crosses.get.name": "Parça çaprazlarını görüntüleme",
    "permissions.article.crosses.get.description": "Parça çapraz referanslarını görüntüleme izni.",
    "permissions.article.crosses.create.name": "Parça çaprazı oluşturma",
    "permissions.article.crosses.create.description": "Parçalar arasında çapraz ilişki oluşturma izni.",
    "permissions.article.crosses.delete.name": "Parça çaprazı silme",
    "permissions.article.crosses.delete.description": "Parçalar arasındaki çapraz ilişkiyi silme izni.",
    "permissions.article.content.create.name": "Parça içeriği oluşturma",
    "permissions.article.content.create.description": "Parça içeriği oluşturma izni.",
    "permissions.article.content.edit.name": "Parça içeriği düzenleme",
    "permissions.article.content.edit.description": "Parça içeriği düzenleme izni.",
    "permissions.article.content.delete.name": "Parça içeriği silme",
    "permissions.article.content.delete.description": "Parça içeriği silme izni.",
    "permissions.article.pair.create.name": "Parça çifti oluşturma",
    "permissions.article.pair.create.description": "Parça çifti oluşturma izni.",
    "permissions.article.pair.edit.name": "Parça çifti düzenleme",
    "permissions.article.pair.edit.description": "Parça çifti düzenleme izni.",
    "permissions.article.pair.delete.name": "Parça çifti silme",
    "permissions.article.pair.delete.description": "Parça çifti silme izni.",
    "permissions.article.images.create.name": "Parça görseli ekleme",
    "permissions.article.images.create.description": "Parçaya görsel ekleme izni.",
    "permissions.article.images.delete.name": "Parça görseli silme",
    "permissions.article.images.delete.description": "Parça görseli silme izni.",
    "permissions.article.reservations.create.name": "Parça rezervasyonu oluşturma",
    "permissions.article.reservations.create.description": "Parça rezervasyonu oluşturma izni.",
    "permissions.article.reservations.edit.name": "Parça rezervasyonu düzenleme",
    "permissions.article.reservations.edit.description": "Parça rezervasyonu düzenleme izni.",
    "permissions.article.reservations.delete.name": "Parça rezervasyonu silme",
    "permissions.article.reservations.delete.description": "Parça rezervasyonu silme izni.",
    "permissions.article.reservations.get.me.name": "Kendi rezervasyonlarını görüntüleme",
    "permissions.article.reservations.get.me.description": "Kendi rezervasyonlarını görüntüleme izni.",
    "permissions.article.reservations.get.all.name": "Tüm rezervasyonları görüntüleme",
    "permissions.article.reservations.get.all.description": "Tüm rezervasyonları görüntüleme izni.",
    "permissions.balances.transaction.create.name": "İşlem oluşturma",
    "permissions.balances.transaction.create.description": "İşlem oluşturma izni.",
    "permissions.balances.transaction.edit.name": "İşlem düzenleme",
    "permissions.balances.transaction.edit.description": "İşlem düzenleme izni.",
    "permissions.balances.transaction.delete.name": "İşlem silme",
    "permissions.balances.transaction.delete.description": "İşlem silme izni.",
    "permissions.balances.transaction.get.all.name": "Tüm işlemleri görüntüleme",
    "permissions.balances.transaction.get.all.description": "Tüm işlemleri görüntüleme izni.",
    "permissions.balances.transaction.get.me.name": "Kendi işlemlerini görüntüleme",
    "permissions.balances.transaction.get.me.description": "Kendi işlemlerini görüntüleme izni.",
    "permissions.balances.finances.update.name": "Kullanıcı finansını güncelleme",
    "permissions.balances.finances.update.description": "Kullanıcı finans bilgilerini güncelleme izni.",
    "permissions.balances.finances.get.name": "Kullanıcı finansını görüntüleme",
    "permissions.balances.finances.get.description": "Kullanıcı finans bilgilerini görüntüleme izni.",
    "permissions.balances.finances.get.me.name": "Kendi finans verilerini görüntüleme",
    "permissions.balances.finances.get.me.description": "Kendi finans verilerini görüntüleme izni.",
    "permissions.currencies.create.name": "Para birimi oluşturma",
    "permissions.currencies.create.description": "Para birimi oluşturma izni.",
    "permissions.currencies.get.name": "Para birimlerini görüntüleme",
    "permissions.currencies.get.description": "Para birimlerini görüntüleme izni.",
    "permissions.markup.create.name": "Kâr marjı kuralı oluşturma",
    "permissions.markup.create.description": "Kâr marjı kuralları oluşturma izni.",
    "permissions.markup.delete.name": "Kâr marjı kuralı silme",
    "permissions.markup.delete.description": "Kâr marjı kuralları silme izni.",
    "permissions.markup.get.name": "Kâr marjı kurallarını görüntüleme",
    "permissions.markup.get.description": "Kâr marjı kurallarını görüntüleme izni.",
    "permissions.markup.set.default.name": "Varsayılan kâr marjı kurallarını ayarlama",
    "permissions.markup.set.default.description": "Varsayılan kâr marjı kurallarını ayarlama izni.",
    "permissions.prices.get.detailed.name": "Detaylı fiyatları görüntüleme",
    "permissions.prices.get.detailed.description": "Detaylı fiyatları görüntüleme izni.",
    "permissions.prices.get.standard.name": "Fiyatları görüntüleme",
    "permissions.prices.get.standard.description": "Fiyatları görüntüleme izni.",
    "permissions.price.appliers.manage.name": "Fiyat uygulayıcılarını yönetme",
    "permissions.price.appliers.manage.description": "Fiyat uygulayıcılarını yönetme izni.",
    "permissions.purchase.create.name": "Satın alma oluşturma",
    "permissions.purchase.create.description": "Satın alma oluşturma izni.",
    "permissions.purchase.edit.name": "Satın alma düzenleme",
    "permissions.purchase.edit.description": "Satın alma düzenleme izni.",
    "permissions.purchase.delete.name": "Satın alma silme",
    "permissions.purchase.delete.description": "Satın alma silme izni.",
    "permissions.purchase.get.name": "Herhangi bir satın almayı görüntüleme",
    "permissions.purchase.get.description": "Herhangi bir satın almayı görüntüleme izni.",
    "permissions.roles.create.name": "Rol oluşturma",
    "permissions.roles.create.description": "Rol oluşturma izni.",
    "permissions.roles.get.name": "Rol görüntüleme",
    "permissions.roles.get.description": "Rol görüntüleme izni.",
    "permissions.roles.permissions.create.name": "Role izin ekleme",
    "permissions.roles.permissions.create.description": "Rollere izin ekleme izni.",
    "permissions.sales.create.name": "Satış oluşturma",
    "permissions.sales.create.description": "Satış oluşturma izni.",
    "permissions.sales.edit.name": "Satış düzenleme",
    "permissions.sales.edit.description": "Satış düzenleme izni.",
    "permissions.sales.delete.name": "Satış silme",
    "permissions.sales.delete.description": "Satış silme izni.",
    "permissions.sales.get.name": "Herhangi bir satışı görüntüleme",
    "permissions.sales.get.description": "Herhangi bir satışı görüntüleme izni.",
    "permissions.storages.create.name": "Depo oluşturma",
    "permissions.storages.create.description": "Depo oluşturma izni.",
    "permissions.storages.edit.name": "Depo düzenleme",
    "permissions.storages.edit.description": "Depo düzenleme izni.",
    "permissions.storages.delete.name": "Depo silme",
    "permissions.storages.delete.description": "Depo silme izni.",
    "permissions.storages.get.name": "Tüm depoları görüntüleme",
    "permissions.storages.get.description": "Tüm depoları görüntüleme izni.",
    "permissions.storages.content.create.name": "Depoya içerik ekleme",
    "permissions.storages.content.create.description": "Depoya içerik ekleme izni.",
    "permissions.storages.content.edit.name": "Depo içeriği düzenleme",
    "permissions.storages.content.edit.description": "Depo içeriği düzenleme izni.",
    "permissions.storages.content.delete.name": "Depo içeriği silme",
    "permissions.storages.content.delete.description": "Depo içeriği silme izni.",
    "permissions.storages.content.get.standard.name": "Temel depo içeriğini görüntüleme",
    "permissions.storages.content.get.standard.description": "Temel depo içeriği verilerini görüntüleme izni.",
    "permissions.storages.content.get.all.name": "Tüm depo içeriğini görüntüleme",
    "permissions.storages.content.get.all.description": "Tüm depo içeriği verilerini görüntüleme izni.",
    "permissions.users.create.name": "Kullanıcı oluşturma",
    "permissions.users.create.description": "Kullanıcı oluşturma izni.",
    "permissions.users.get.name": "Tüm kullanıcıları görüntüleme",
    "permissions.users.get.description": "Tüm kullanıcıları görüntüleme izni.",
    "permissions.users.info.get.name": "Kullanıcı bilgisini görüntüleme",
    "permissions.users.info.get.description": "Kullanıcı bilgilerini görüntüleme izni.",
    "permissions.users.permissions.create.name": "Kullanıcıya izin ekleme",
    "permissions.users.permissions.create.description": "Kullanıcıya izin ekleme izni.",
    "permissions.users.roles.create.name": "Kullanıcıya rol ekleme",
    "permissions.users.roles.create.description": "Kullanıcıya rol ekleme izni.",
    "permissions.users.discount.create.name": "Kullanıcı indirimi düzenleme",
    "permissions.users.discount.create.description": "Kullanıcı indirimini düzenleme izni.",
    "permissions.users.discount.get.name": "Kullanıcı indirimini görüntüleme",
    "permissions.users.discount.get.description": "Kullanıcı indirimini görüntüleme izni.",
    "permissions.users.mails.create.name": "Kurumsal e-posta oluşturma",
    "permissions.users.mails.create.description": "Kullanıcı için kurumsal e-posta oluşturma izni.",
    "permissions.users.vehicles.create.me.name": "Kendi garajına araç ekleme",
    "permissions.users.vehicles.create.me.description": "Kendi garajına araç ekleme izni.",
    "permissions.users.vehicles.create.all.name": "Herhangi bir garaja araç ekleme",
    "permissions.users.vehicles.create.all.description": "Herhangi bir garaja araç ekleme izni.",
    "permissions.users.storages.add.name": "Kullanıcıya depo ekleme",
    "permissions.users.storages.add.description": "Kullanıcıya depo ekleme izni.",
    "permissions.users.storages.get.name": "Kullanıcı depolarını görüntüleme",
    "permissions.users.storages.get.description": "Kullanıcı depolarını görüntüleme izni.",
    "permissions.users.storages.delete.name": "Kullanıcı deposunu silme",
    "permissions.users.storages.delete.description": "Kullanıcı deposunu silme izni.",
    "permissions.organizations.get.name": "Kuruluşları görüntüleme",
    "permissions.organizations.get.description": "Kuruluşları arama ve görüntüleme izni.",
    "permissions.permissions.create.name": "İzin oluşturma",
    "permissions.permissions.create.description": "İzin oluşturma izni.",
    "permissions.permissions.get.name": "Tüm izinleri görüntüleme",
    "permissions.permissions.get.description": "Tüm izinleri görüntüleme izni.",
    "permissions.cart.add.name": "Sepete ekleme",
    "permissions.cart.add.description": "Sepete ürün ekleme izni.",
    "permissions.cart.get.name": "Sepeti görüntüleme",
    "permissions.cart.get.description": "Sepeti görüntüleme izni.",
    "permissions.cart.delete.name": "Sepetten kaldırma",
    "permissions.cart.delete.description": "Sepetten ürün kaldırma izni.",
    "permissions.cart.update.name": "Sepeti güncelleme",
    "permissions.cart.update.description": "Sepetteki ürün miktarlarını güncelleme izni.",
    "permissions.options.get.name": "Ayarları görüntüleme",
    "permissions.options.get.description": "Ayarları görüntüleme izni.",
    "permissions.storage.routes.get.name": "Rotaları görüntüleme",
    "permissions.storage.routes.get.description": "Rotaları görüntüleme izni.",
    "permissions.storage.routes.create.name": "Rota oluşturma",
    "permissions.storage.routes.create.description": "Rota oluşturma izni.",
    "permissions.storage.routes.edit.name": "Rota düzenleme",
    "permissions.storage.routes.edit.description": "Rota düzenleme izni.",
    "permissions.storage.routes.delete.name": "Rota silme",
    "permissions.storage.routes.delete.description": "Rota silme izni.",
    "permissions.logistics.calculate.name": "Lojistik hesaplama",
    "permissions.logistics.calculate.description": "Lojistik hesaplamalarını alma izni.",
    "permissions.uploads.create.name": "Belge yükleme oluşturma",
    "permissions.uploads.create.description": "Belge yükleme oluşturma izni.",
    "permissions.jobs.create.name": "Görev oluşturma",
    "permissions.jobs.create.description": "Görev oluşturma izni.",
    "permissions.jobs.get.name": "Görevleri görüntüleme",
    "permissions.jobs.get.description": "Görevleri görüntüleme izni.",
    "permissions.metrics.create.name": "Metrik oluşturma",
    "permissions.metrics.create.description": "Metrik oluşturma izni.",
    "permissions.metrics.get.name": "Metrikleri görüntüleme",
    "permissions.metrics.get.description": "Metrikleri görüntüleme izni."
  }
}
